omniblack/caddy/__init__.py
omniblack/caddy/attr_cls.py
omniblack/caddy/client.py
omniblack/caddy/convert_json.py
omniblack/caddy/route.py
omniblack/caddy/unix.py
omniblack.caddy-0.0.6.post2.dist-info/LICENSE.txt
omniblack.caddy-0.0.6.post2.dist-info/METADATA
omniblack.caddy-0.0.6.post2.dist-info/WHEEL
omniblack.caddy-0.0.6.post2.dist-info/top_level.txt
omniblack.caddy-0.0.6.post2.dist-info/RECORD
