Metadata-Version: 2.1
Name: omniblack.caddy
Version: 0.0.6.post2
Summary: A python client for Caddy's admin api.
Author-email: Terry Patterson <Terryp@wegrok.net>
License: 
Project-URL: Homepage, https://gitlab.com/terryp/terry/-/tree/next/lib/caddy
Project-URL: Repository, https://gitlab.com/terryp/terry.git
Classifier: Development Status :: 3 - Alpha
Classifier: Intended Audience :: Developers
License-File: LICENSE.txt
Requires-Dist: attrs
Requires-Dist: requests
Requires-Dist: multidict
Requires-Dist: urllib3
Requires-Dist: pydantic
